{
	"info": {
		"_postman_id": "9b462313-0743-4193-b805-0b8d2b11c0ca",
		"name": "knowledge-base",
		"schema": "https://schema.getpostman.com/json/collection/v2.1.0/collection.json",
		"_exporter_id": "30209139"
	},
	"item": [
		{
			"name": "topic",
			"item": [
				{
					"name": "add topic",
					"request": {
						"method": "POST",
						"header": [],
						"body": {
							"mode": "formdata",
							"formdata": [
								{
									"key": "name",
									"value": "",
									"type": "text"
								}
							]
						},
						"url": {
							"raw": "http://localhost:8080/topic-api/v1/topic",
							"protocol": "http",
							"host": [
								"localhost"
							],
							"port": "8080",
							"path": [
								"topic-api",
								"v1",
								"topic"
							]
						}
					},
					"response": []
				},
				{
					"name": "rename topic",
					"request": {
						"method": "PUT",
						"header": [],
						"body": {
							"mode": "formdata",
							"formdata": [
								{
									"key": "id",
									"value": "",
									"type": "text"
								},
								{
									"key": "name",
									"value": "",
									"type": "text"
								}
							]
						},
						"url": {
							"raw": "http://localhost:8080/topic-api/v1/topic",
							"protocol": "http",
							"host": [
								"localhost"
							],
							"port": "8080",
							"path": [
								"topic-api",
								"v1",
								"topic"
							]
						}
					},
					"response": []
				},
				{
					"name": "delete topic",
					"request": {
						"method": "DELETE",
						"header": [],
						"body": {
							"mode": "formdata",
							"formdata": [
								{
									"key": "id",
									"value": "",
									"type": "text"
								}
							]
						},
						"url": {
							"raw": "http://localhost:8080/topic-api/v1/topic",
							"protocol": "http",
							"host": [
								"localhost"
							],
							"port": "8080",
							"path": [
								"topic-api",
								"v1",
								"topic"
							]
						}
					},
					"response": []
				},
				{
					"name": "get all topics",
					"protocolProfileBehavior": {
						"disableBodyPruning": true
					},
					"request": {
						"method": "GET",
						"header": [],
						"body": {
							"mode": "formdata",
							"formdata": []
						},
						"url": {
							"raw": "http://localhost:8080/topic-api/v1/topics",
							"protocol": "http",
							"host": [
								"localhost"
							],
							"port": "8080",
							"path": [
								"topic-api",
								"v1",
								"topics"
							]
						}
					},
					"response": []
				}
			]
		},
		{
			"name": "doc",
			"item": [
				{
					"name": "add doc",
					"request": {
						"method": "POST",
						"header": [],
						"body": {
							"mode": "formdata",
							"formdata": [
								{
									"key": "topicId",
									"value": "",
									"type": "text"
								},
								{
									"key": "name",
									"value": "",
									"type": "text"
								},
								{
									"key": "docxFile",
									"type": "file",
									"src": []
								}
							]
						},
						"url": {
							"raw": "http://localhost:8080/doc-api/v1/doc",
							"protocol": "http",
							"host": [
								"localhost"
							],
							"port": "8080",
							"path": [
								"doc-api",
								"v1",
								"doc"
							]
						}
					},
					"response": []
				},
				{
					"name": "get pdf",
					"protocolProfileBehavior": {
						"disableBodyPruning": true
					},
					"request": {
						"method": "GET",
						"header": [],
						"body": {
							"mode": "formdata",
							"formdata": [
								{
									"key": "id",
									"value": "",
									"type": "text"
								}
							]
						},
						"url": {
							"raw": "http://localhost:8080/doc-api/v1/doc/pdf",
							"protocol": "http",
							"host": [
								"localhost"
							],
							"port": "8080",
							"path": [
								"doc-api",
								"v1",
								"doc",
								"pdf"
							]
						}
					},
					"response": []
				},
				{
					"name": "get docx",
					"protocolProfileBehavior": {
						"disableBodyPruning": true
					},
					"request": {
						"method": "GET",
						"header": [],
						"body": {
							"mode": "formdata",
							"formdata": [
								{
									"key": "id",
									"value": "",
									"type": "text"
								}
							]
						},
						"url": {
							"raw": "http://localhost:8080/doc-api/v1/doc/docx",
							"protocol": "http",
							"host": [
								"localhost"
							],
							"port": "8080",
							"path": [
								"doc-api",
								"v1",
								"doc",
								"docx"
							]
						}
					},
					"response": []
				},
				{
					"name": "get all docs",
					"request": {
						"method": "GET",
						"header": [],
						"url": {
							"raw": "http://localhost:8080/doc-api/v1/docs",
							"protocol": "http",
							"host": [
								"localhost"
							],
							"port": "8080",
							"path": [
								"doc-api",
								"v1",
								"docs"
							]
						}
					},
					"response": []
				},
				{
					"name": "rename doc",
					"request": {
						"method": "PUT",
						"header": [],
						"body": {
							"mode": "formdata",
							"formdata": [
								{
									"key": "id",
									"value": "",
									"type": "text"
								},
								{
									"key": "name",
									"value": "",
									"type": "text"
								}
							]
						},
						"url": {
							"raw": "http://localhost:8080/doc-api/v1/doc/name",
							"protocol": "http",
							"host": [
								"localhost"
							],
							"port": "8080",
							"path": [
								"doc-api",
								"v1",
								"doc",
								"name"
							]
						}
					},
					"response": []
				},
				{
					"name": "replace file",
					"request": {
						"method": "PUT",
						"header": [],
						"body": {
							"mode": "formdata",
							"formdata": [
								{
									"key": "id",
									"value": "",
									"type": "text"
								},
								{
									"key": "docxFile",
									"type": "file",
									"src": []
								}
							]
						},
						"url": {
							"raw": "http://localhost:8080/doc-api/v1/doc/docx",
							"protocol": "http",
							"host": [
								"localhost"
							],
							"port": "8080",
							"path": [
								"doc-api",
								"v1",
								"doc",
								"docx"
							]
						}
					},
					"response": []
				},
				{
					"name": "delete doc",
					"request": {
						"method": "DELETE",
						"header": [],
						"body": {
							"mode": "formdata",
							"formdata": [
								{
									"key": "id",
									"value": "",
									"type": "text"
								}
							]
						},
						"url": {
							"raw": "http://localhost:8080/doc-api/v1/doc",
							"protocol": "http",
							"host": [
								"localhost"
							],
							"port": "8080",
							"path": [
								"doc-api",
								"v1",
								"doc"
							]
						}
					},
					"response": []
				}
			]
		}
	]
}